<annotation>
	<folder></folder>
	<filename>IMG_20220527_174724_jpg.rf.46cdfcecae9929967a2ce6d598973cb4.jpg</filename>
	<path>IMG_20220527_174724_jpg.rf.46cdfcecae9929967a2ce6d598973cb4.jpg</path>
	<source>
		<database>roboflow.com</database>
	</source>
	<size>
		<width>640</width>
		<height>640</height>
		<depth>3</depth>
	</size>
	<segmented>0</segmented>
	<object>
		<name>Motorbike</name>
		<pose>Unspecified</pose>
		<truncated>0</truncated>
		<difficult>0</difficult>
		<occluded>0</occluded>
		<bndbox>
			<xmin>307</xmin>
			<xmax>539</xmax>
			<ymin>426</ymin>
			<ymax>641</ymax>
		</bndbox>
	</object>
	<object>
		<name>Motorbike</name>
		<pose>Unspecified</pose>
		<truncated>0</truncated>
		<difficult>0</difficult>
		<occluded>0</occluded>
		<bndbox>
			<xmin>78</xmin>
			<xmax>132</xmax>
			<ymin>363</ymin>
			<ymax>407</ymax>
		</bndbox>
	</object>
	<metadata>
	</metadata>
</annotation>
